nive/__init__.py
nive/application.py
nive/container.py
nive/definitions.py
nive/events.py
nive/helper.py
nive/i18n.py
nive/objects.py
nive/portal.py
nive/registration.py
nive/search.py
nive/security.py
nive/tool.py
nive/views.py
nive/workflow.py
nive/components/__init__.py
nive/components/adminview/__init__.py
nive/components/adminview/form.pt
nive/components/adminview/help.pt
nive/components/adminview/index.pt
nive/components/adminview/modules.pt
nive/components/adminview/root.pt
nive/components/adminview/tools.pt
nive/components/adminview/view.py
nive/components/adminview/views.pt
nive/components/adminview/static/adminview.css
nive/components/adminview/static/icon_license.txt
nive/components/adminview/static/icon_reload.svg
nive/components/adminview/static/logo.png
nive/components/adminview/static/mods/jquery-3.3.1.slim.min.js
nive/components/adminview/static/mods/jquery.min.js
nive/components/adminview/static/mods/bootstrap-4.3.1-dist/css/bootstrap-grid.css
nive/components/adminview/static/mods/bootstrap-4.3.1-dist/css/bootstrap-grid.css.map
nive/components/adminview/static/mods/bootstrap-4.3.1-dist/css/bootstrap-grid.min.css
nive/components/adminview/static/mods/bootstrap-4.3.1-dist/css/bootstrap-grid.min.css.map
nive/components/adminview/static/mods/bootstrap-4.3.1-dist/css/bootstrap-reboot.css
nive/components/adminview/static/mods/bootstrap-4.3.1-dist/css/bootstrap-reboot.css.map
nive/components/adminview/static/mods/bootstrap-4.3.1-dist/css/bootstrap-reboot.min.css
nive/components/adminview/static/mods/bootstrap-4.3.1-dist/css/bootstrap-reboot.min.css.map
nive/components/adminview/static/mods/bootstrap-4.3.1-dist/css/bootstrap.css
nive/components/adminview/static/mods/bootstrap-4.3.1-dist/css/bootstrap.css.map
nive/components/adminview/static/mods/bootstrap-4.3.1-dist/css/bootstrap.min.css
nive/components/adminview/static/mods/bootstrap-4.3.1-dist/css/bootstrap.min.css.map
nive/components/adminview/static/mods/bootstrap-4.3.1-dist/js/bootstrap.bundle.js
nive-1.6.9.dist-info/METADATA
nive-1.6.9.dist-info/WHEEL
nive-1.6.9.dist-info/top_level.txt
nive-1.6.9.dist-info/RECORD
